odoo/addons/hr_employee_document/README.rst
odoo/addons/hr_employee_document/__init__.py
odoo/addons/hr_employee_document/__manifest__.py
odoo/addons/hr_employee_document/i18n/fr.po
odoo/addons/hr_employee_document/i18n/hr.po
odoo/addons/hr_employee_document/i18n/hr_employee_document.pot
odoo/addons/hr_employee_document/models/__init__.py
odoo/addons/hr_employee_document/models/hr_employee.py
odoo/addons/hr_employee_document/readme/CONTRIBUTORS.rst
odoo/addons/hr_employee_document/readme/DESCRIPTION.rst
odoo/addons/hr_employee_document/static/description/icon.png
odoo/addons/hr_employee_document/static/description/index.html
odoo/addons/hr_employee_document/tests/__init__.py
odoo/addons/hr_employee_document/tests/test_hr_employee_document.py
odoo/addons/hr_employee_document/views/hr_employee.xml
odoo12_addon_hr_employee_document-12.0.1.1.0.dist-info/METADATA
odoo12_addon_hr_employee_document-12.0.1.1.0.dist-info/WHEEL
odoo12_addon_hr_employee_document-12.0.1.1.0.dist-info/top_level.txt
odoo12_addon_hr_employee_document-12.0.1.1.0.dist-info/RECORD
